odoo8_addon_attachment_lock-8.0.1.0.0.99.dev1-py2.7-nspkg.pth
odoo8_addon_attachment_lock-8.0.1.0.0.99.dev1.dist-info/METADATA
odoo8_addon_attachment_lock-8.0.1.0.0.99.dev1.dist-info/RECORD
odoo8_addon_attachment_lock-8.0.1.0.0.99.dev1.dist-info/WHEEL
odoo8_addon_attachment_lock-8.0.1.0.0.99.dev1.dist-info/namespace_packages.txt
odoo8_addon_attachment_lock-8.0.1.0.0.99.dev1.dist-info/top_level.txt
odoo_addons/attachment_lock/README.rst
odoo_addons/attachment_lock/__init__.py
odoo_addons/attachment_lock/__openerp__.py
odoo_addons/attachment_lock/data/ir_cron.xml
odoo_addons/attachment_lock/models/__init__.py
odoo_addons/attachment_lock/models/ir_attachment.py
odoo_addons/attachment_lock/models/ir_attachment_lock.py
odoo_addons/attachment_lock/security/ir.model.access.csv
odoo_addons/attachment_lock/security/ir_rule.xml
odoo_addons/attachment_lock/security/res_groups.xml
odoo_addons/attachment_lock/static/description/icon.png
odoo_addons/attachment_lock/static/src/css/attachment_lock.css
odoo_addons/attachment_lock/static/src/js/attachment_lock.js
odoo_addons/attachment_lock/static/src/xml/attachment_lock.xml
odoo_addons/attachment_lock/tests/__init__.py
odoo_addons/attachment_lock/tests/test_attachment_lock.py
odoo_addons/attachment_lock/views/ir_attachment_lock.xml
odoo_addons/attachment_lock/views/templates.xml
